[
    {
        "categoryName": "Grocery",
        "parentId" : "5e1196cf66e4693a1e84904c",
        "type": 2   ,
        "hasChild" : 1,
        "location": {
            "type": "Point",
            "coordinates": [30.704649,76.717873]
           }
    },
    {
        "categoryName": "Food Items",
        "parentId" : "5e1196cf66e4693a1e84904c",
        "type": 2   ,
        "hasChild" : 1,
        "location": {
            "type": "Point",
            "coordinates": [30.704649,76.717873]
           }
    },
    {
        "categoryName": "Sweets",
        "parentId" : "5e1196cf66e4693a1e84904c",
        "type": 2   ,
        "hasChild" : 1,
        "location": {
            "type": "Point",
            "coordinates": [30.704649,76.717873]
           }
    },
    {
        "categoryName": "General Items",
        "parentId" : "5e1196cf66e4693a1e84904c",
        "type": 2   ,
        "hasChild" : 1,
        "location": {
            "type": "Point",
            "coordinates": [30.704649,76.717873]
           }
    },
    {
        "categoryName": "Vegetables",
        "parentId" : "5e1196cf66e4693a1e84904c",
        "type": 2   ,
        "hasChild" : 1,
        "location": {
            "type": "Point",
            "coordinates": [30.704649,76.717873]
           }
    }
]